{
    "801080374783508521": {
        "AFK": {}
    },
    "793108599869931580": {
        "AFK": {}
    },
    "783547639944839178": {
        "AFK": {}
    },
    "865548525289996298": {
        "AFK": {}
    },
    "854071489871478854": {
        "AFK": {}
    },
    "866367736887246849": {
        "AFK": {}
    },
    "887728913671942205": {
        "AFK": {}
    },
    "900027110310166590": {
        "AFK": {}
    },
    "902118136348803102": {
        "AFK": {}
    },
    "920676440066883624": {
        "AFK": {}
    },
    "868422571673128990": {
        "AFK": {}
    },
    "924407093560225862": {
        "AFK": {}
    },
    "927285122313642064": {
        "AFK": {}
    },
    "786462454078898207": {
        "AFK": {}
    },
    "881326757016387614": {
        "AFK": {}
    },
    "927682699035021353": {
        "AFK": {}
    },
    "933311804401143859": {
        "AFK": {}
    },
    "939607695957315614": {
        "AFK": {}
    },
    "934480423592001576": {
        "AFK": {}
    },
    "944952077451427850": {
        "AFK": {}
    },
    "758260448251346975": {
        "AFK": {}
    },
    "946084420807426078": {
        "AFK": {}
    },
    "956497990128898068": {
        "AFK": {}
    },
    "975422192030474240": {
        "AFK": {}
    },
    "993333839034323045": {
        "AFK": {}
    },
    "989131278521597973": {
        "AFK": {}
    },
    "869487421438443580": {
        "AFK": {}
    },
    "870796402735849533": {
        "AFK": {}
    },
    "993450836233555968": {
        "AFK": {}
    },
    "1058765685666361395": {
        "AFK": {}
    },
    "1057557665942880276": {
        "AFK": {}
    }
}